poepy/__init__.py
poepy/data.py
poepy/poem.py
poepy/poepy.py
poepy/conf/poems.rc
poepy/data/Baxter1992.tsv
poepy/data/CJP.tsv
poepy/data/Eichendorff1815.tsv
poepy/data/Wang1980.tsv
poepy/data/Weingarten2016.tsv
poepy/data/borges.txt
poepy/data/dylan.txt
poepy/data/eichendorff.txt
poepy/data/eminem.txt
poepy/data/leto.txt
poepy/data/mey.txt
poepy/data/miguel.txt
poepy/data/moustaki.txt
poepy/data/references.bib
poepy/data/rodriguez.txt
poepy/data/yueliang.txt
poepy-0.2.0.dist-info/LICENSE.txt
poepy-0.2.0.dist-info/METADATA
poepy-0.2.0.dist-info/RECORD
poepy-0.2.0.dist-info/WHEEL
poepy-0.2.0.dist-info/top_level.txt
