Metadata-Version: 2.1
Name: poepy
Version: 0.2.0
Summary: A Python library for handling annotated rhymes.
Home-page: https://github.com/lingpy/poepy
Author: Johann-Mattis List
Author-email: list@shh.mpg.de
License: GPL
Keywords: Chinese linguistics,historical linguistics,computer-assisted language comparison
Platform: UNKNOWN
Provides-Extra: test
Requires-Dist: clldutils
Requires-Dist: lingpy
Provides-Extra: test
Requires-Dist: pytest; extra == 'test'
Requires-Dist: pytest-coverage; extra == 'test'
